[{"type":"file","link":"./images/Kali-Palmeriem-Matraman.jpg","box":[113.05,69,11.75,5.9],"label":"sampah"},
{"type":"file","link":"./images/Kali-Palmeriem-Matraman.jpg","box":[83.8,82.25,9.7,8.1],"label":"sampah"},
{"type":"file","link":"./images/Kali-Palmeriem-Matraman.jpg","box":[123.25,88.8,10,7.2],"label":"sampah"},
{"type":"file","link":"./images/Kali-Palmeriem-Matraman.jpg","box":[102.6,89.4,15,8.45],"label":"sampah"},
{"type":"file","link":"./images/Kali-Palmeriem-Matraman.jpg","box":[148.85,102.9,15.95,11.25],"label":"sampah"},
{"type":"file","link":"./images/Kali-Palmeriem-Matraman.jpg","box":[123.85,108.2,23.75,11.85],"label":"sampah"},
{"type":"file","link":"./images/Kali-Palmeriem-Matraman.jpg","box":[60.05,112.3,6.25,9.35],"label":"sampah"},
{"type":"file","link":"./images/Kali-Palmeriem-Matraman.jpg","box":[74.15,117.6,14.7,10.65],"label":"sampah"},
{"type":"file","link":"./images/Kali-Palmeriem-Matraman.jpg","box":[122.6,124.45,23.75,13.75],"label":"sampah"},
{"type":"file","link":"./images/Kali-Palmeriem-Matraman.jpg","box":[95.05,128.8,25.05,13.15],"label":"sampah"},
{"type":"file","link":"./images/Kali-Palmeriem-Matraman.jpg","box":[143.85,141.05,24.1,10.95],"label":"sampah"},
{"type":"file","link":"./images/Kali-Palmeriem-Matraman.jpg","box":[55.05,148.85,21.25,13.1],"label":"sampah"},
{"type":"file","link":"./images/Kali-Palmeriem-Matraman.jpg","box":[101.3,153.85,19.4,16.25],"label":"sampah"},
{"type":"file","link":"./images/Kali-Palmeriem-Matraman.jpg","box":[194.2,161.4,18.8,11.85],"label":"sampah"},
{"type":"file","link":"./images/Kali-Palmeriem-Matraman.jpg","box":[170.45,164.2,16.9,12.2],"label":"sampah"},
{"type":"file","link":"./images/Kali-Palmeriem-Matraman.jpg","box":[47.55,170.15,10.65,8.75],"label":"sampah"},
{"type":"file","link":"./images/Kali-Palmeriem-Matraman.jpg","box":[132.6,180.1,36.25,17.5],"label":"sampah"},
{"type":"file","link":"./images/Kali-Palmeriem-Matraman.jpg","box":[60.05,227.65,45.65,19.4],"label":"sampah"}
]